ran/__init__.py
ran/ran_jit.py
Ran_JIT-0.0.5.dist-info/LICENSE.txt
Ran_JIT-0.0.5.dist-info/METADATA
Ran_JIT-0.0.5.dist-info/WHEEL
Ran_JIT-0.0.5.dist-info/top_level.txt
Ran_JIT-0.0.5.dist-info/RECORD
