Metadata-Version: 2.1
Name: Ran-JIT
Version: 0.0.5
Summary: A python lib when imported boosts your code using JIT
Home-page: 
Author: Coden
Author-email: codenrblx@gmail.com
License: MIT
Keywords: booster
Classifier: Development Status :: 5 - Production/Stable
Classifier: Intended Audience :: Education
Classifier: Operating System :: Microsoft :: Windows :: Windows 10
Classifier: License :: OSI Approved :: MIT License
Classifier: Programming Language :: Python :: 3
License-File: LICENSE.txt
Requires-Dist: numba (>=0.53.1)
Requires-Dist: psutil (>=5.8.0)
